holidays_plus/__init__.py
holidays_plus-0.0.2.dist-info/LICENSE
holidays_plus-0.0.2.dist-info/METADATA
holidays_plus-0.0.2.dist-info/WHEEL
holidays_plus-0.0.2.dist-info/top_level.txt
holidays_plus-0.0.2.dist-info/RECORD
