Metadata-Version: 2.1
Name: holidays-plus
Version: 0.0.2
Summary: Enhanced add-on for the holidays library offering expanded functionality
Home-page: https://github.com/samtregar/python-holidays-plus
Author: Sam Tregar
Author-email: sam@tregar.com
License: UNKNOWN
Platform: UNKNOWN
Classifier: Programming Language :: Python :: 3
Classifier: License :: OSI Approved :: Apache Software License
Classifier: Operating System :: OS Independent
Requires-Python: >=3.6
Requires-Dist: holidays
